{
	"$schema": "../feature.schema.json",
	"id": "db-drizzle",
	"name": "Drizzle ORM",
	"description": "SQL database integration with Drizzle ORM and type-safe queries",
	"dependencies": {
		"drizzle-orm": "^0.36.4"
	},
	"devDependencies": {
		"drizzle-kit": "^0.30.1"
	},
	"scripts": {
		"db:generate": "drizzle-kit generate",
		"db:migrate": "drizzle-kit migrate",
		"db:studio": "drizzle-kit studio"
	},
	"conflicts": ["db-prisma"],
	"imports": [
		"import { DatabaseService } from \"./db\";"
	],
	"moduleConfig": {
		"providers": ["DatabaseService"]
	}
}
